image_processing/__init__.py
image_processing/processing/__init__.py
image_processing/processing/combination.py
image_processing/processing/transformation.py
image_processing/utils/__init__.py
image_processing/utils/io.py
image_processing/utils/plot.py
Image_Processing_Peralta-0.0.1.dist-info/METADATA
Image_Processing_Peralta-0.0.1.dist-info/WHEEL
Image_Processing_Peralta-0.0.1.dist-info/top_level.txt
Image_Processing_Peralta-0.0.1.dist-info/RECORD
