Metadata-Version: 2.1
Name: Image-Processing-Peralta
Version: 0.0.1
Summary: A project that will too a images matchmaking and also show their diferences.
Home-page: https://github.com/joaofilipe014/image-processing-package.git
Author: João Filipe Peralta
Author-email: joaofilipeperalta@gmail.com
Requires-Python: >=3.8
